pysofaconventions/SOFAAPI.py
pysofaconventions/SOFAAttributes.py
pysofaconventions/SOFAEmitter.py
pysofaconventions/SOFAError.py
pysofaconventions/SOFAFile.py
pysofaconventions/SOFAListener.py
pysofaconventions/SOFANcFile.py
pysofaconventions/SOFAPositionVariable.py
pysofaconventions/SOFAReceiver.py
pysofaconventions/SOFASource.py
pysofaconventions/SOFAUnits.py
pysofaconventions/SOFAVersion.py
pysofaconventions/SOFAWarning.py
pysofaconventions/__init__.py
pysofaconventions/SOFAConventions/SOFAAmbisonicsDRIR.py
pysofaconventions/SOFAConventions/SOFAGeneralFIR.py
pysofaconventions/SOFAConventions/SOFAGeneralFIRE.py
pysofaconventions/SOFAConventions/SOFAGeneralTF.py
pysofaconventions/SOFAConventions/SOFAMultiSpeakerBRIR.py
pysofaconventions/SOFAConventions/SOFASimpleFreeFieldHRIR.py
pysofaconventions/SOFAConventions/SOFASimpleFreeFieldSOS.py
pysofaconventions/SOFAConventions/SOFASimpleHeadphoneIR.py
pysofaconventions/SOFAConventions/SOFASingleRoom.py
pysofaconventions/SOFAConventions/SOFASingleRoomDRIR.py
pysofaconventions/SOFAConventions/__init__.py
tests/__init__.py
tests/test_SOFAAPI.py
tests/test_SOFAAmbisonicsDRIR.py
tests/test_SOFAAttributes.py
tests/test_SOFAEmitter.py
tests/test_SOFAFile.py
tests/test_SOFAGeneralFIR.py
tests/test_SOFAGeneralFIRE.py
tests/test_SOFAGeneralTF.py
tests/test_SOFAListener.py
tests/test_SOFAMultiSpeakerBRIR.py
tests/test_SOFANcFile.py
tests/test_SOFAReceiver.py
tests/test_SOFASimpleFreeFieldHRIR.py
tests/test_SOFASimpleFreeFieldSOS.py
tests/test_SOFASimpleHeadphoneIR.py
tests/test_SOFASingleRoomDRIR.py
tests/test_SOFASource.py
tests/test_SOFAUnits.py
pysofaconventions-0.1.5.dist-info/LICENSE
pysofaconventions-0.1.5.dist-info/METADATA
pysofaconventions-0.1.5.dist-info/WHEEL
pysofaconventions-0.1.5.dist-info/top_level.txt
pysofaconventions-0.1.5.dist-info/RECORD
